LICENSE
MANIFEST.in
README.md
setup.py
toraio/__init__.py
toraio/_client_session.py
toraio/_pool.py
toraio/_proxy.py
toraio/_ua.py
toraio/_util.py
toraio/proxy.py
toraio.egg-info/PKG-INFO
toraio.egg-info/SOURCES.txt
toraio.egg-info/dependency_links.txt
toraio.egg-info/requires.txt
toraio.egg-info/top_level.txt
toraio/bin/linux/Data/Browser/profiles.ini
toraio/bin/linux/Data/Browser/profile.default/bookmarks.html
toraio/bin/linux/Data/Browser/profile.default/extensions/{73a6fe31-595d-460b-a920-fcc0f8843232}.xpi
toraio/bin/linux/Data/Tor/geoip
toraio/bin/linux/Data/Tor/geoip6
toraio/bin/linux/Data/Tor/torrc
toraio/bin/linux/Data/Tor/torrc-defaults
toraio/bin/linux/Data/fontconfig/fonts.conf
toraio/bin/linux/Tor/libcrypto.so.1.1
toraio/bin/linux/Tor/libevent-2.1.so.7
toraio/bin/linux/Tor/libssl.so.1.1
toraio/bin/linux/Tor/tor
toraio/bin/linux/Tor/PluggableTransports/obfs4proxy
toraio/bin/linux/Tor/PluggableTransports/snowflake-client
toraio/bin/linux/Tor/libstdc++/libstdc++.so.6
toraio/bin/win32/Data/Tor/geoip
toraio/bin/win32/Data/Tor/geoip6
toraio/bin/win32/Tor/libcrypto-1_1-x64.dll
toraio/bin/win32/Tor/libcrypto-1_1.dll
toraio/bin/win32/Tor/libevent-2-1-7.dll
toraio/bin/win32/Tor/libevent_core-2-1-7.dll
toraio/bin/win32/Tor/libevent_extra-2-1-7.dll
toraio/bin/win32/Tor/libgcc_s_seh-1.dll
toraio/bin/win32/Tor/libgcc_s_sjlj-1.dll
toraio/bin/win32/Tor/libssl-1_1-x64.dll
toraio/bin/win32/Tor/libssl-1_1.dll
toraio/bin/win32/Tor/libssp-0.dll
toraio/bin/win32/Tor/libwinpthread-1.dll
toraio/bin/win32/Tor/tor-gencert.exe
toraio/bin/win32/Tor/tor.exe
toraio/bin/win32/Tor/zlib1.dll