Metadata-Version: 2.1
Name: toraio
Version: 1.0.8
Summary: UNKNOWN
Home-page: https://github.com/ultrafunkamsterdam/toraio
Author: UltrafunkAmsterdam
Author-email: 
License: MIT
Platform: UNKNOWN
License-File: LICENSE
